Workbook
Name Slicer_Account: #N/A

Sheet Charts of Accounts
B1: Sample Legacy Pvt Limited
B2: Charts of Accounts
B3: For the Year 30 june 2024
B4: Account Categories | C4: Sub Account | D4: Label-Financial Statement | E4: Indiviual Account | F4: Sub Account
B5: Assets | C5: Non-Current Assets | D5: Balace Sheet | E5: Cash | F5: Current Assets
B6: Liablity | C6: Current Assets | D6: Balace Sheet | E6: Equity | F6: Equity
B7: Equity | C7: Non-Current Liablity | D7: Balace Sheet | E7: Bank | F7: Current Assets
B8: Expenses | C8: Current Liablity | D8: Balace Sheet | E8: Mega Mart-Vendor | F8: Current Liablity
B9: Revenue | C9: Equity | D9: Balace Sheet | E9: Inventory | F9: Current Assets
C10: Revenue | D10: Income Statement | E10: Sale | F10: Revenue
C11: Expense | D11: Income Statement | E11: Mr.Rehman-Customer | F11: Current Assets
E12: Office Supplier | F12: Expense
E13: Computer | F13: Non-Current Assets
E14: Salaries | F14: Expense
E15: Rent | F15: Expense
E16: Entertainment Expense | F16: Expense
E17: Cost of Goods Sold | F17: Expense
E18: Tax | F18: Expense
E19: Govt | F19: Current Liablity

Sheet Genral Entries
B1: Sample Legacy Pvt Limited
B2: Charts of Accounts
B3: For the Year 30 june 2024
B4: Date | C4: Description | D4: Account | E4: Debit | F4: Credit | G4: Details/Narration
B5: 45108 | C5: Established Business | D5: Cash | E5: 5000000 | G5: Started Business with 5,000,000/- with Cash on 1st July 2023.
B6: 45108 | C6: Established Business | D6: Equity | F6: =E5 -> 5000000
B7: 45109 | C7: Cash Deposited into bank | D7: Bank | E7: 1500000 | G7: Deposited 1,500,000/- in Bank on 2nd July 2023.
B8: 45109 | C8: Cash Deposited into bank | D8: Cash | F8: =E7 -> 1500000
B9: 45112 | C9: Inventory Purchased | D9: Inventory | E9: 750000 | G9: Inventory purchased of 750,000 on credit from Mega Mart on 5 July 2023
B10: 45112 | C10: Inventory Purchased | D10: Mega Mart-Vendor | F10: =E9 -> 750000
B11: 45114 | C11: Inventory Purchased | D11: Cash | E11: 500000 | G11: Inventory purchased of 500,000 from Multi Media on 7 July 2023.
B12: 45114 | C12: Inventory Purchased | D12: Bank | F12: =E11 -> 500000
B13: 45117 | C13: Inventory Sold | D13: Mr.Rehman-Customer | E13: 800000 | G13: Sold inventory on Credit to Mr. Rehman of 400,000 on 10 July 2023.
B14: 45117 | C14: Inventory Sold | D14: Sale | F14: =E13 -> 800000
B15: 45121 | C15: Inventory Sold | D15: Cash | E15: 425000 | G15: Sold inventory on Cash of 300,000 on 14 July 2023.
B16: 45121 | C16: Inventory Sold | D16: Sale | F16: =E15 -> 425000
B17: 45122 | C17: Inventory Adjustment | D17: Cost of Goods Sold | E17: 290000
B18: 45122 | C18: Inventory Adjustment | D18: Inventory | F18: =E17 -> 290000
B19: 45122 | C19: Inventory Adjustment | D19: Cost of Goods Sold | E19: 200000
B20: 45122 | C20: Inventory Adjustment | D20: Inventory | F20: =E19 -> 200000
B21: 45123 | C21: Expense Incurred | D21: Office Supplier | E21: 45000 | G21: Expenses incurred in office of 45,000 on 16 July 2023.
B22: 45123 | C22: Expense Incurred | D22: Bank | F22: =E21 -> 45000
B23: 45125 | C23: Entertainment Expense | D23: Entertainment Expense | E23: 70000 | G23: Entertainment Expenses incurred of 70,000 on 18 July 2023.
B24: 45125 | C24: Entertainment Expense | D24: Bank | F24: =E23 -> 70000
B25: 45126 | C25: Computer Purchased | D25: Computer | E25: 250000 | G25: Computer purchased for 250,000 on 27 July 2023.
B26: 45127 | C26: Computer Purchased | D26: Bank | F26: =E25 -> 250000
B27: 45139 | C27: Salary Paid | D27: Salaries | E27: 110000 | G27: Salary Paid on 1st August for 110,000/-
B28: 45139 | C28: Salary Paid | D28: Bank | F28: =E27 -> 110000
B29: 45140 | C29: Rent Paid | D29: Rent | E29: 35000 | G29: Rent paid to Mr. Abbas on 2nd Aug of 35,000/-
B30: 45140 | C30: Rent Paid | D30: Bank | F30: =E29 -> 35000
B31: 45140 | C31: Tax Working Adj. | D31: Tax | E31: 142500
B32: 45140 | C32: Tax Working Adj. | D32: Govt | F32: =E31 -> 142500

Sheet Ledger
A1: Ledger
A2: =B4 -> Sale
A3: Date | B3: Account | C3: Sum of Debit | D3: Sum of Credit | E3: Sum of Balance
A4: 10-Jul | B4: Sale | D4: 800000 | E4: -800000
A5: 14-Jul | B5: Sale | D5: 425000 | E5: -425000
A6: Grand Total | D6: 1225000 | E6: -1225000

Sheet Trail Balance
A1: Account | B1: Sum of Debit | C1: Sum of Credit | D1: Sum of Balance | E1: Sub-Account | F1: Label to FS
A2: Bank | B2: 1500000 | C2: 1010000 | D2: 490000 | E2: Current Assets | F2: Balace Sheet
A3: Cash | B3: 5925000 | C3: 1500000 | D3: 4425000 | E3: Current Assets | F3: Balace Sheet
A4: Computer | B4: 250000 | D4: 250000 | E4: Non-Current Assets | F4: Balace Sheet
A5: Entertainment Expense | B5: 70000 | D5: 70000 | E5: Expense | F5: Income Statement
A6: Equity | C6: 5000000 | D6: -5000000 | E6: Equity | F6: Balace Sheet
A7: Inventory | B7: 750000 | C7: 490000 | D7: 260000 | E7: Current Assets | F7: Balace Sheet
A8: Mega Mart-Vendor | C8: 750000 | D8: -750000 | E8: Current Liablity | F8: Balace Sheet
A9: Mr.Rehman-Customer | B9: 800000 | D9: 800000 | E9: Current Assets | F9: Balace Sheet
A10: Office Supplier | B10: 45000 | D10: 45000 | E10: Expense | F10: Income Statement
A11: Rent | B11: 35000 | D11: 35000 | E11: Expense | F11: Income Statement
A12: Salaries | B12: 110000 | D12: 110000 | E12: Expense | F12: Income Statement
A13: Sale | C13: 1225000 | D13: -1225000 | E13: Revenue | F13: Income Statement
A14: Cost of Goods Sold | B14: 490000 | D14: 490000 | E14: Expense | F14: Income Statement
A15: Govt | C15: 142500 | D15: -142500 | E15: Current Liablity | F15: Balace Sheet
A16: Tax | B16: 142500 | D16: 142500 | E16: Expense | F16: Income Statement
A17: Grand Total | B17: 10117500 | C17: 10117500 | D17: 0

Sheet Income Statement
B1: Sample Legacy Pvt Limited
B2: Income Statement
B3: For the Year ended June 30, 2024
B5: Revenue | D5: Amount (PKR) | E5: Amount (PKR)
C6: Sale | E6: =-VLOOKUP(C6,'Trail Balance'!$A$2:$D$14,4,0) -> 1225000
C7: Cost of Goods Sold | E7: =-VLOOKUP(C7,'Trail Balance'!$A$2:$D$14,4,0) -> -490000
B9: Gross Profit | E9: =E6+E7 -> 735000
B11: Operating Expense
C12: Office Supplier | D12: =VLOOKUP(C12,'Trail Balance'!$A$2:$D$14,4,0) -> 45000
C13: Rent | D13: =VLOOKUP(C13,'Trail Balance'!$A$2:$D$14,4,0) -> 35000
C14: Salaries | D14: =VLOOKUP(C14,'Trail Balance'!$A$2:$D$14,4,0) -> 110000
C15: Entertainment Expense | D15: =VLOOKUP(C15,'Trail Balance'!$A$2:$D$14,4,0) -> 70000
E16: =SUM(D12:D15) -> 260000
B17: Operating profit | E17: =E9-E16 -> 475000
C18: Tax-30% | E18: =E17*0.3 -> 142500
B19: Net Profit | E19: =E17-E18 -> 332500

Sheet Balance Sheet
B1: Sample Legacy Pvt Limited
B2: BalanceSheet
B3: As at June 30, 2024
B5: Assets | E5: Amount (PKR)
B6: Non-Current Assets
C7: Computer | E7: =VLOOKUP(C7,'Trail Balance'!$A$2:$D$15,4,0) -> 250000
B9: Total Non-Current Assets | E9: =E7 -> 250000
B11: Current Assets
C12: Bank | E12: =VLOOKUP(C12,'Trail Balance'!$A$2:$D$15,4,0) -> 490000
C13: Cash | E13: =VLOOKUP(C13,'Trail Balance'!$A$2:$D$15,4,0) -> 4425000
C14: Inventory | E14: =VLOOKUP(C14,'Trail Balance'!$A$2:$D$15,4,0) -> 260000
C15: Mr.Rehman-Customer | E15: =VLOOKUP(C15,'Trail Balance'!$A$2:$D$15,4,0) -> 800000
E17: =SUM(E12:E15) -> 5975000
B19: Total Assets | E19: =E9+E17 -> 6225000
B21: Liabilities and Equity
B22: Non-Current Liabilities | D22: -
B24: Total Non-Current Liabilities | D24: -
B26: Current Liabilities
C27: Mega Mart-Vendor | D27: =-VLOOKUP(C27,'Trail Balance'!$A$2:$D$15,4,0) -> 750000
C28: Govt | D28: =-VLOOKUP(C28,'Trail Balance'!$A$2:$D$15,4,0) -> 142500
E29: =SUM(D27:D28) -> 892500
B30: Total Current Liabilities | E30: =D27+D28 -> 892500
B32: Equity
C33: Equity | D33: 5000000
C34: Net Income | D34: 332500
E35: =D33+D34 -> 5332500
B36: Total Equity | E36: =E35 -> 5332500
B38: Total Liabilities and Equity | E38: =E30+E36 -> 6225000
C40: Check | E40: =E19-E38 -> 0
